odoo/addons/product_equivalent_category/README.rst
odoo/addons/product_equivalent_category/__init__.py
odoo/addons/product_equivalent_category/__manifest__.py
odoo/addons/product_equivalent_category/i18n/ca.po
odoo/addons/product_equivalent_category/i18n/es.po
odoo/addons/product_equivalent_category/i18n/it.po
odoo/addons/product_equivalent_category/i18n/product_equivalent_category.pot
odoo/addons/product_equivalent_category/i18n/pt.po
odoo/addons/product_equivalent_category/models/__init__.py
odoo/addons/product_equivalent_category/models/product_equivalent_category.py
odoo/addons/product_equivalent_category/models/product_template.py
odoo/addons/product_equivalent_category/readme/CONTRIBUTORS.rst
odoo/addons/product_equivalent_category/readme/DESCRIPTION.rst
odoo/addons/product_equivalent_category/readme/USAGE.rst
odoo/addons/product_equivalent_category/security/ir.model.access.csv
odoo/addons/product_equivalent_category/static/description/icon.png
odoo/addons/product_equivalent_category/static/description/index.html
odoo/addons/product_equivalent_category/views/product_equivalent_category_views.xml
odoo/addons/product_equivalent_category/views/product_template_views.xml
odoo12_addon_product_equivalent_category-12.0.1.0.0.99.dev11.dist-info/METADATA
odoo12_addon_product_equivalent_category-12.0.1.0.0.99.dev11.dist-info/WHEEL
odoo12_addon_product_equivalent_category-12.0.1.0.0.99.dev11.dist-info/top_level.txt
odoo12_addon_product_equivalent_category-12.0.1.0.0.99.dev11.dist-info/RECORD
