Metadata-Version: 2.1
Name: odoo12-addon-product-equivalent-category
Version: 12.0.1.0.0.99.dev11
Summary: This module adds the concept of equivalent category. A product can belong to a certain equivalent category and all products in that category will be considered equivalent.
Home-page: https://github.com/OCA/product-attribute
Author: ForgeFlow S.L., Odoo Community Association (OCA)
Author-email: support@odoo-community.org
License: AGPL-3
Platform: UNKNOWN
Classifier: Programming Language :: Python
Classifier: Framework :: Odoo
Classifier: Framework :: Odoo :: 12.0
Classifier: License :: OSI Approved :: GNU Affero General Public License v3
Requires-Python: >=3.5
Requires-Dist: odoo <12.1dev,>=12.0a
